chronos_forecaster/__init__.py
chronos_forecaster/forecaster.py
chronos_forecaster/engines/__init__.py
chronos_forecaster/engines/chronos2_engine.py
chronos_forecaster/engines/chronos_engine.py
chronos_forecaster-0.2.2.dist-info/licenses/LICENSE
chronos_forecaster-0.2.2.dist-info/METADATA
chronos_forecaster-0.2.2.dist-info/WHEEL
chronos_forecaster-0.2.2.dist-info/top_level.txt
chronos_forecaster-0.2.2.dist-info/RECORD
