Metadata-Version: 2.4
Name: chronos_forecaster
Version: 0.2.2
Summary: Unified interface for Amazon Chronos and Chronos-2 time series forecasting engines.
Author: Sebastião Santos Lessa
Author-email: sebastiao2002@gmail.com
License: MIT
Classifier: Programming Language :: Python :: 3
Classifier: License :: OSI Approved :: MIT License
Classifier: Operating System :: OS Independent
Requires-Python: >=3.10
License-File: LICENSE
Requires-Dist: chronos-forecasting
Requires-Dist: setuptools
Requires-Dist: pandas
Requires-Dist: torch
Requires-Dist: boto3
Dynamic: author
Dynamic: author-email
Dynamic: classifier
Dynamic: license
Dynamic: license-file
Dynamic: requires-dist
Dynamic: requires-python
Dynamic: summary
